{"cameraMode":{"drawMode":0,"name":"Shaded","section":"Shading Mode"},"sceneLighting":true,"audioPlay":false,"sceneViewState":{"m_AlwaysRefresh":false,"showFog":true,"showSkybox":true,"showFlares":true,"showImageEffects":true,"showParticleSystems":true,"showVisualEffectGraphs":true,"m_FxEnabled":true},"in2DMode":false,"pivot":{"x":3.6996726989746095,"y":-5.595126152038574,"z":59.18242645263672},"rotation":{"x":-0.08022207766771317,"y":-0.047238148748874667,"z":0.0038065053522586824,"w":-0.9956648349761963},"size":39.032188415527347,"orthographic":false}